{
  "metadata" : {
    "identifier" : "https://www.nettruyento.com/truyen-tranh/con-duong-sung-dan-57020",
    "title" : "Con Đường Súng Đạn - Chapter 76: ORENO WAGAMAMA",
    "subtitle" : null,
    "author" : null,
    "narrator" : null,
    "language" : "vi",
    "description" : null,
    "publisher" : "N/A",
    "subject" : null,
    "modified" : null,
    "published" : "2023-06-10",
    "duration" : 0,
    "abridged" : false,
    "conformsTo" : "https://readium.org/webpub-manifest/profiles/divina",
    "numberOfPages" : 86,
    "readingProgression" : "ttb",
    "belongsTo" : null,
    "presentation" : {
      "fit" : "width",
      "overflow" : "scrolled",
      "continuous" : true
    },
    "@type" : null,
    "schema:license" : null
  },
  "links" : [ {
    "rel" : "self",
    "href" : "https://raw.githubusercontent.com/thuvienonline40/book_storage_collection/main/comic_manifest.json",
    "type" : "application/divina+json"
  } ],
  "readingOrder" : [ {
    "href" : "https://raw.githubusercontent.com/tsvhcomic28/comic_storage8/main/IMAGE/IMAGE_79d5628b6bde5292e751fb18372635a9_8dd908e991fdb8429b4702eacca0d6cb_78a39e6f12ce6d3d0c5f74956c6ba982.jpg",
    "type" : "image/jpeg",
    "bitrate" : 0,
    "duration" : 0,
    "title" : null,
    "properties" : null,
    "alternate" : [ {
      "href" : "https://i8.ntcdntempv3.com/data/images/5702/672173/001.jpg?data=net",
      "type" : "image/jpeg",
      "bitrate" : 0,
      "duration" : 0,
      "title" : null,
      "properties" : null,
      "alternate" : null
    } ]
  }, {
    "href" : "https://raw.githubusercontent.com/tsvhcomic28/comic_storage8/main/IMAGE/IMAGE_79d5628b6bde5292e751fb18372635a9_8dd908e991fdb8429b4702eacca0d6cb_1f1333b37250f2a553ca5e45d40e40ab.jpg",
    "type" : "image/jpeg",
    "bitrate" : 0,
    "duration" : 0,
    "title" : null,
    "properties" : null,
    "alternate" : [ {
      "href" : "https://i8.ntcdntempv3.com/data/images/5702/672173/002.jpg?data=net",
      "type" : "image/jpeg",
      "bitrate" : 0,
      "duration" : 0,
      "title" : null,
      "properties" : null,
      "alternate" : null
    } ]
  }, {
    "href" : "https://raw.githubusercontent.com/tsvhcomic28/comic_storage8/main/IMAGE/IMAGE_79d5628b6bde5292e751fb18372635a9_8dd908e991fdb8429b4702eacca0d6cb_36358fcfca06ad044abb43f2b5318fc4.jpg",
    "type" : "image/jpeg",
    "bitrate" : 0,
    "duration" : 0,
    "title" : null,
    "properties" : null,
    "alternate" : [ {
      "href" : "https://i8.ntcdntempv3.com/data/images/5702/672173/003.jpg?data=net",
      "type" : "image/jpeg",
      "bitrate" : 0,
      "duration" : 0,
      "title" : null,
      "properties" : null,
      "alternate" : null
    } ]
  }, {
    "href" : "https://raw.githubusercontent.com/tsvhcomic28/comic_storage8/main/IMAGE/IMAGE_79d5628b6bde5292e751fb18372635a9_8dd908e991fdb8429b4702eacca0d6cb_0b4aa035f22719c6cd80ee78edd9ce2d.jpg",
    "type" : "image/jpeg",
    "bitrate" : 0,
    "duration" : 0,
    "title" : null,
    "properties" : null,
    "alternate" : [ {
      "href" : "https://i8.ntcdntempv3.com/data/images/5702/672173/004.jpg?data=net",
      "type" : "image/jpeg",
      "bitrate" : 0,
      "duration" : 0,
      "title" : null,
      "properties" : null,
      "alternate" : null
    } ]
  }, {
    "href" : "https://raw.githubusercontent.com/tsvhcomic28/comic_storage8/main/IMAGE/IMAGE_79d5628b6bde5292e751fb18372635a9_8dd908e991fdb8429b4702eacca0d6cb_1f0548e6ee9e22ef6b4b0fa6474ea4ab.jpg",
    "type" : "image/jpeg",
    "bitrate" : 0,
    "duration" : 0,
    "title" : null,
    "properties" : null,
    "alternate" : [ {
      "href" : "https://i8.ntcdntempv3.com/data/images/5702/672173/005.jpg?data=net",
      "type" : "image/jpeg",
      "bitrate" : 0,
      "duration" : 0,
      "title" : null,
      "properties" : null,
      "alternate" : null
    } ]
  }, {
    "href" : "https://raw.githubusercontent.com/tsvhcomic28/comic_storage8/main/IMAGE/IMAGE_79d5628b6bde5292e751fb18372635a9_8dd908e991fdb8429b4702eacca0d6cb_af20e28bd0583308cf2345d937343e33.jpg",
    "type" : "image/jpeg",
    "bitrate" : 0,
    "duration" : 0,
    "title" : null,
    "properties" : null,
    "alternate" : [ {
      "href" : "https://i8.ntcdntempv3.com/data/images/5702/672173/006.jpg?data=net",
      "type" : "image/jpeg",
      "bitrate" : 0,
      "duration" : 0,
      "title" : null,
      "properties" : null,
      "alternate" : null
    } ]
  }, {
    "href" : "https://raw.githubusercontent.com/tsvhcomic28/comic_storage8/main/IMAGE/IMAGE_79d5628b6bde5292e751fb18372635a9_8dd908e991fdb8429b4702eacca0d6cb_f4673ca09f7f6f41f246504eb853a6eb.jpg",
    "type" : "image/jpeg",
    "bitrate" : 0,
    "duration" : 0,
    "title" : null,
    "properties" : null,
    "alternate" : [ {
      "href" : "https://i8.ntcdntempv3.com/data/images/5702/672173/007.jpg?data=net",
      "type" : "image/jpeg",
      "bitrate" : 0,
      "duration" : 0,
      "title" : null,
      "properties" : null,
      "alternate" : null
    } ]
  }, {
    "href" : "https://raw.githubusercontent.com/tsvhcomic28/comic_storage8/main/IMAGE/IMAGE_79d5628b6bde5292e751fb18372635a9_8dd908e991fdb8429b4702eacca0d6cb_cb50cf8f4db032c919ac7bbc4d497f14.jpg",
    "type" : "image/jpeg",
    "bitrate" : 0,
    "duration" : 0,
    "title" : null,
    "properties" : null,
    "alternate" : [ {
      "href" : "https://i8.ntcdntempv3.com/data/images/5702/672173/008.jpg?data=net",
      "type" : "image/jpeg",
      "bitrate" : 0,
      "duration" : 0,
      "title" : null,
      "properties" : null,
      "alternate" : null
    } ]
  }, {
    "href" : "https://raw.githubusercontent.com/tsvhcomic28/comic_storage8/main/IMAGE/IMAGE_79d5628b6bde5292e751fb18372635a9_8dd908e991fdb8429b4702eacca0d6cb_1cd92c03e587da99ebc7a2f6b9597a31.jpg",
    "type" : "image/jpeg",
    "bitrate" : 0,
    "duration" : 0,
    "title" : null,
    "properties" : null,
    "alternate" : [ {
      "href" : "https://i8.ntcdntempv3.com/data/images/5702/672173/009.jpg?data=net",
      "type" : "image/jpeg",
      "bitrate" : 0,
      "duration" : 0,
      "title" : null,
      "properties" : null,
      "alternate" : null
    } ]
  }, {
    "href" : "https://raw.githubusercontent.com/tsvhcomic28/comic_storage8/main/IMAGE/IMAGE_79d5628b6bde5292e751fb18372635a9_8dd908e991fdb8429b4702eacca0d6cb_d5dc02b1b46845441aeffe16acd57b48.jpg",
    "type" : "image/jpeg",
    "bitrate" : 0,
    "duration" : 0,
    "title" : null,
    "properties" : null,
    "alternate" : [ {
      "href" : "https://i8.ntcdntempv3.com/data/images/5702/672173/010.jpg?data=net",
      "type" : "image/jpeg",
      "bitrate" : 0,
      "duration" : 0,
      "title" : null,
      "properties" : null,
      "alternate" : null
    } ]
  }, {
    "href" : "https://raw.githubusercontent.com/tsvhcomic28/comic_storage8/main/IMAGE/IMAGE_79d5628b6bde5292e751fb18372635a9_8dd908e991fdb8429b4702eacca0d6cb_375d5b86180374db4fc7cbd71ad99bf7.jpg",
    "type" : "image/jpeg",
    "bitrate" : 0,
    "duration" : 0,
    "title" : null,
    "properties" : null,
    "alternate" : [ {
      "href" : "https://i8.ntcdntempv3.com/data/images/5702/672173/011.jpg?data=net",
      "type" : "image/jpeg",
      "bitrate" : 0,
      "duration" : 0,
      "title" : null,
      "properties" : null,
      "alternate" : null
    } ]
  }, {
    "href" : "https://raw.githubusercontent.com/tsvhcomic28/comic_storage8/main/IMAGE/IMAGE_79d5628b6bde5292e751fb18372635a9_8dd908e991fdb8429b4702eacca0d6cb_c463673f626ea56f026aaa895e0e5add.jpg",
    "type" : "image/jpeg",
    "bitrate" : 0,
    "duration" : 0,
    "title" : null,
    "properties" : null,
    "alternate" : [ {
      "href" : "https://i8.ntcdntempv3.com/data/images/5702/672173/012.jpg?data=net",
      "type" : "image/jpeg",
      "bitrate" : 0,
      "duration" : 0,
      "title" : null,
      "properties" : null,
      "alternate" : null
    } ]
  }, {
    "href" : "https://raw.githubusercontent.com/tsvhcomic28/comic_storage8/main/IMAGE/IMAGE_79d5628b6bde5292e751fb18372635a9_8dd908e991fdb8429b4702eacca0d6cb_b9bdccea7cb61b5d845e5ab1310735e4.jpg",
    "type" : "image/jpeg",
    "bitrate" : 0,
    "duration" : 0,
    "title" : null,
    "properties" : null,
    "alternate" : [ {
      "href" : "https://i8.ntcdntempv3.com/data/images/5702/672173/013.jpg?data=net",
      "type" : "image/jpeg",
      "bitrate" : 0,
      "duration" : 0,
      "title" : null,
      "properties" : null,
      "alternate" : null
    } ]
  }, {
    "href" : "https://raw.githubusercontent.com/tsvhcomic28/comic_storage8/main/IMAGE/IMAGE_79d5628b6bde5292e751fb18372635a9_8dd908e991fdb8429b4702eacca0d6cb_92a837e87ea3694ea8ded7cc9f42dc8f.jpg",
    "type" : "image/jpeg",
    "bitrate" : 0,
    "duration" : 0,
    "title" : null,
    "properties" : null,
    "alternate" : [ {
      "href" : "https://i8.ntcdntempv3.com/data/images/5702/672173/014.jpg?data=net",
      "type" : "image/jpeg",
      "bitrate" : 0,
      "duration" : 0,
      "title" : null,
      "properties" : null,
      "alternate" : null
    } ]
  }, {
    "href" : "https://raw.githubusercontent.com/tsvhcomic28/comic_storage8/main/IMAGE/IMAGE_79d5628b6bde5292e751fb18372635a9_8dd908e991fdb8429b4702eacca0d6cb_890cac5a41e645e8e2313f266791c77e.jpg",
    "type" : "image/jpeg",
    "bitrate" : 0,
    "duration" : 0,
    "title" : null,
    "properties" : null,
    "alternate" : [ {
      "href" : "https://i8.ntcdntempv3.com/data/images/5702/672173/015.jpg?data=net",
      "type" : "image/jpeg",
      "bitrate" : 0,
      "duration" : 0,
      "title" : null,
      "properties" : null,
      "alternate" : null
    } ]
  }, {
    "href" : "https://raw.githubusercontent.com/tsvhcomic28/comic_storage8/main/IMAGE/IMAGE_79d5628b6bde5292e751fb18372635a9_8dd908e991fdb8429b4702eacca0d6cb_ca0f4ba57660831054e12c1d01854201.jpg",
    "type" : "image/jpeg",
    "bitrate" : 0,
    "duration" : 0,
    "title" : null,
    "properties" : null,
    "alternate" : [ {
      "href" : "https://i8.ntcdntempv3.com/data/images/5702/672173/016.jpg?data=net",
      "type" : "image/jpeg",
      "bitrate" : 0,
      "duration" : 0,
      "title" : null,
      "properties" : null,
      "alternate" : null
    } ]
  }, {
    "href" : "https://raw.githubusercontent.com/tsvhcomic28/comic_storage8/main/IMAGE/IMAGE_79d5628b6bde5292e751fb18372635a9_8dd908e991fdb8429b4702eacca0d6cb_0866d921aad551baf6a09fd03c067e9a.jpg",
    "type" : "image/jpeg",
    "bitrate" : 0,
    "duration" : 0,
    "title" : null,
    "properties" : null,
    "alternate" : [ {
      "href" : "https://i8.ntcdntempv3.com/data/images/5702/672173/017.jpg?data=net",
      "type" : "image/jpeg",
      "bitrate" : 0,
      "duration" : 0,
      "title" : null,
      "properties" : null,
      "alternate" : null
    } ]
  }, {
    "href" : "https://raw.githubusercontent.com/tsvhcomic28/comic_storage8/main/IMAGE/IMAGE_79d5628b6bde5292e751fb18372635a9_8dd908e991fdb8429b4702eacca0d6cb_d11bc6cd0993234a90fcb5af07a88bdd.jpg",
    "type" : "image/jpeg",
    "bitrate" : 0,
    "duration" : 0,
    "title" : null,
    "properties" : null,
    "alternate" : [ {
      "href" : "https://i8.ntcdntempv3.com/data/images/5702/672173/018.jpg?data=net",
      "type" : "image/jpeg",
      "bitrate" : 0,
      "duration" : 0,
      "title" : null,
      "properties" : null,
      "alternate" : null
    } ]
  }, {
    "href" : "https://raw.githubusercontent.com/tsvhcomic28/comic_storage8/main/IMAGE/IMAGE_79d5628b6bde5292e751fb18372635a9_8dd908e991fdb8429b4702eacca0d6cb_63ae0a59e0ca91856dc82f7e848ab910.jpg",
    "type" : "image/jpeg",
    "bitrate" : 0,
    "duration" : 0,
    "title" : null,
    "properties" : null,
    "alternate" : [ {
      "href" : "https://i8.ntcdntempv3.com/data/images/5702/672173/019.jpg?data=net",
      "type" : "image/jpeg",
      "bitrate" : 0,
      "duration" : 0,
      "title" : null,
      "properties" : null,
      "alternate" : null
    } ]
  }, {
    "href" : "https://raw.githubusercontent.com/tsvhcomic28/comic_storage8/main/IMAGE/IMAGE_79d5628b6bde5292e751fb18372635a9_8dd908e991fdb8429b4702eacca0d6cb_0a584acdcde1279bc22334bafea3a770.jpg",
    "type" : "image/jpeg",
    "bitrate" : 0,
    "duration" : 0,
    "title" : null,
    "properties" : null,
    "alternate" : [ {
      "href" : "https://i8.ntcdntempv3.com/data/images/5702/672173/020.jpg?data=net",
      "type" : "image/jpeg",
      "bitrate" : 0,
      "duration" : 0,
      "title" : null,
      "properties" : null,
      "alternate" : null
    } ]
  }, {
    "href" : "https://raw.githubusercontent.com/tsvhcomic28/comic_storage8/main/IMAGE/IMAGE_79d5628b6bde5292e751fb18372635a9_8dd908e991fdb8429b4702eacca0d6cb_2e32d0a80d638f6be57a5619726417aa.jpg",
    "type" : "image/jpeg",
    "bitrate" : 0,
    "duration" : 0,
    "title" : null,
    "properties" : null,
    "alternate" : [ {
      "href" : "https://i8.ntcdntempv3.com/data/images/5702/672173/021.jpg?data=net",
      "type" : "image/jpeg",
      "bitrate" : 0,
      "duration" : 0,
      "title" : null,
      "properties" : null,
      "alternate" : null
    } ]
  }, {
    "href" : "https://raw.githubusercontent.com/tsvhcomic28/comic_storage8/main/IMAGE/IMAGE_79d5628b6bde5292e751fb18372635a9_8dd908e991fdb8429b4702eacca0d6cb_f31dbb96ad8aad03e4e0ba5b984ef8b0.jpg",
    "type" : "image/jpeg",
    "bitrate" : 0,
    "duration" : 0,
    "title" : null,
    "properties" : null,
    "alternate" : [ {
      "href" : "https://i8.ntcdntempv3.com/data/images/5702/672173/022.jpg?data=net",
      "type" : "image/jpeg",
      "bitrate" : 0,
      "duration" : 0,
      "title" : null,
      "properties" : null,
      "alternate" : null
    } ]
  }, {
    "href" : "https://raw.githubusercontent.com/tsvhcomic28/comic_storage8/main/IMAGE/IMAGE_79d5628b6bde5292e751fb18372635a9_8dd908e991fdb8429b4702eacca0d6cb_4d59dd6f636aca51fe3486ea39589329.jpg",
    "type" : "image/jpeg",
    "bitrate" : 0,
    "duration" : 0,
    "title" : null,
    "properties" : null,
    "alternate" : [ {
      "href" : "https://i8.ntcdntempv3.com/data/images/5702/672173/023.jpg?data=net",
      "type" : "image/jpeg",
      "bitrate" : 0,
      "duration" : 0,
      "title" : null,
      "properties" : null,
      "alternate" : null
    } ]
  }, {
    "href" : "https://raw.githubusercontent.com/tsvhcomic28/comic_storage8/main/IMAGE/IMAGE_79d5628b6bde5292e751fb18372635a9_8dd908e991fdb8429b4702eacca0d6cb_78b696b7a7af81bfdcf01a05e68959f6.jpg",
    "type" : "image/jpeg",
    "bitrate" : 0,
    "duration" : 0,
    "title" : null,
    "properties" : null,
    "alternate" : [ {
      "href" : "https://i8.ntcdntempv3.com/data/images/5702/672173/024.jpg?data=net",
      "type" : "image/jpeg",
      "bitrate" : 0,
      "duration" : 0,
      "title" : null,
      "properties" : null,
      "alternate" : null
    } ]
  }, {
    "href" : "https://raw.githubusercontent.com/tsvhcomic28/comic_storage8/main/IMAGE/IMAGE_79d5628b6bde5292e751fb18372635a9_8dd908e991fdb8429b4702eacca0d6cb_634e662198b09fd3b5e2e687a76782e7.jpg",
    "type" : "image/jpeg",
    "bitrate" : 0,
    "duration" : 0,
    "title" : null,
    "properties" : null,
    "alternate" : [ {
      "href" : "https://i8.ntcdntempv3.com/data/images/5702/672173/025.jpg?data=net",
      "type" : "image/jpeg",
      "bitrate" : 0,
      "duration" : 0,
      "title" : null,
      "properties" : null,
      "alternate" : null
    } ]
  }, {
    "href" : "https://raw.githubusercontent.com/tsvhcomic28/comic_storage8/main/IMAGE/IMAGE_79d5628b6bde5292e751fb18372635a9_8dd908e991fdb8429b4702eacca0d6cb_127e97fe84fae322e9eaad695ea32830.jpg",
    "type" : "image/jpeg",
    "bitrate" : 0,
    "duration" : 0,
    "title" : null,
    "properties" : null,
    "alternate" : [ {
      "href" : "https://i8.ntcdntempv3.com/data/images/5702/672173/026.jpg?data=net",
      "type" : "image/jpeg",
      "bitrate" : 0,
      "duration" : 0,
      "title" : null,
      "properties" : null,
      "alternate" : null
    } ]
  }, {
    "href" : "https://raw.githubusercontent.com/tsvhcomic28/comic_storage8/main/IMAGE/IMAGE_79d5628b6bde5292e751fb18372635a9_8dd908e991fdb8429b4702eacca0d6cb_2ef52aae28e921c3ea1765494dcda1f8.jpg",
    "type" : "image/jpeg",
    "bitrate" : 0,
    "duration" : 0,
    "title" : null,
    "properties" : null,
    "alternate" : [ {
      "href" : "https://i8.ntcdntempv3.com/data/images/5702/672173/027.jpg?data=net",
      "type" : "image/jpeg",
      "bitrate" : 0,
      "duration" : 0,
      "title" : null,
      "properties" : null,
      "alternate" : null
    } ]
  }, {
    "href" : "https://raw.githubusercontent.com/tsvhcomic28/comic_storage8/main/IMAGE/IMAGE_79d5628b6bde5292e751fb18372635a9_8dd908e991fdb8429b4702eacca0d6cb_d8eaea98aad4d9fa5f48468ac1e2aca7.jpg",
    "type" : "image/jpeg",
    "bitrate" : 0,
    "duration" : 0,
    "title" : null,
    "properties" : null,
    "alternate" : [ {
      "href" : "https://i8.ntcdntempv3.com/data/images/5702/672173/028.jpg?data=net",
      "type" : "image/jpeg",
      "bitrate" : 0,
      "duration" : 0,
      "title" : null,
      "properties" : null,
      "alternate" : null
    } ]
  }, {
    "href" : "https://raw.githubusercontent.com/tsvhcomic28/comic_storage8/main/IMAGE/IMAGE_79d5628b6bde5292e751fb18372635a9_8dd908e991fdb8429b4702eacca0d6cb_a1800c466d47c8bdf966279404aa8ed6.jpg",
    "type" : "image/jpeg",
    "bitrate" : 0,
    "duration" : 0,
    "title" : null,
    "properties" : null,
    "alternate" : [ {
      "href" : "https://i8.ntcdntempv3.com/data/images/5702/672173/029.jpg?data=net",
      "type" : "image/jpeg",
      "bitrate" : 0,
      "duration" : 0,
      "title" : null,
      "properties" : null,
      "alternate" : null
    } ]
  }, {
    "href" : "https://raw.githubusercontent.com/tsvhcomic28/comic_storage8/main/IMAGE/IMAGE_79d5628b6bde5292e751fb18372635a9_8dd908e991fdb8429b4702eacca0d6cb_e0874d34749a5d8ed217eec3d9ec854b.jpg",
    "type" : "image/jpeg",
    "bitrate" : 0,
    "duration" : 0,
    "title" : null,
    "properties" : null,
    "alternate" : [ {
      "href" : "https://i8.ntcdntempv3.com/data/images/5702/672173/030.jpg?data=net",
      "type" : "image/jpeg",
      "bitrate" : 0,
      "duration" : 0,
      "title" : null,
      "properties" : null,
      "alternate" : null
    } ]
  }, {
    "href" : "https://raw.githubusercontent.com/tsvhcomic28/comic_storage8/main/IMAGE/IMAGE_79d5628b6bde5292e751fb18372635a9_8dd908e991fdb8429b4702eacca0d6cb_f252d21013398cc3440c5550c382d293.jpg",
    "type" : "image/jpeg",
    "bitrate" : 0,
    "duration" : 0,
    "title" : null,
    "properties" : null,
    "alternate" : [ {
      "href" : "https://i8.ntcdntempv3.com/data/images/5702/672173/031.jpg?data=net",
      "type" : "image/jpeg",
      "bitrate" : 0,
      "duration" : 0,
      "title" : null,
      "properties" : null,
      "alternate" : null
    } ]
  }, {
    "href" : "https://raw.githubusercontent.com/tsvhcomic28/comic_storage8/main/IMAGE/IMAGE_79d5628b6bde5292e751fb18372635a9_8dd908e991fdb8429b4702eacca0d6cb_9a71acf36ee07c280c4cfea4ed76e956.jpg",
    "type" : "image/jpeg",
    "bitrate" : 0,
    "duration" : 0,
    "title" : null,
    "properties" : null,
    "alternate" : [ {
      "href" : "https://i8.ntcdntempv3.com/data/images/5702/672173/032.jpg?data=net",
      "type" : "image/jpeg",
      "bitrate" : 0,
      "duration" : 0,
      "title" : null,
      "properties" : null,
      "alternate" : null
    } ]
  } ],
  "toc" : null,
  "@context" : "https://readium.org/webpub-manifest/context.jsonld"
}