{
  "metadata" : {
    "identifier" : "https://www.nettruyento.com/truyen-tranh/dao-hai-tac-91690",
    "title" : "Đảo Hải Tặc - Chapter 954",
    "subtitle" : null,
    "author" : null,
    "narrator" : null,
    "language" : "vi",
    "description" : null,
    "publisher" : "N/A",
    "subject" : null,
    "modified" : null,
    "published" : "2023-05-16",
    "duration" : 0,
    "abridged" : false,
    "conformsTo" : "https://readium.org/webpub-manifest/profiles/divina",
    "numberOfPages" : 1090,
    "readingProgression" : "ttb",
    "belongsTo" : null,
    "presentation" : {
      "fit" : "width",
      "overflow" : "scrolled",
      "continuous" : true
    },
    "@type" : null,
    "schema:license" : null
  },
  "links" : [ {
    "rel" : "self",
    "href" : "https://raw.githubusercontent.com/thuvienonline40/book_storage_collection/main/comic_manifest.json",
    "type" : "application/divina+json"
  } ],
  "readingOrder" : [ {
    "href" : "https://raw.githubusercontent.com/tsvhcomic18alt1/comic_storage_two8/main/IMAGE/IMAGE_1a70f98b26bce0122a92571c3bcce3f5_d602b889440aaef330b2719e0ef5551d_6ade334655ee92b5a7ac22de49870b98.jpg",
    "type" : "image/jpeg",
    "bitrate" : 0,
    "duration" : 0,
    "title" : null,
    "properties" : null,
    "alternate" : [ {
      "href" : "https://i221.ntcdntempv3.com/data/images/9169/500721/001.jpg?data=net",
      "type" : "image/jpeg",
      "bitrate" : 0,
      "duration" : 0,
      "title" : null,
      "properties" : null,
      "alternate" : null
    } ]
  }, {
    "href" : "https://raw.githubusercontent.com/tsvhcomic18alt1/comic_storage_two8/main/IMAGE/IMAGE_1a70f98b26bce0122a92571c3bcce3f5_d602b889440aaef330b2719e0ef5551d_af5187d38be4dcf2a1e8019d4ec95245.jpg",
    "type" : "image/jpeg",
    "bitrate" : 0,
    "duration" : 0,
    "title" : null,
    "properties" : null,
    "alternate" : [ {
      "href" : "https://i221.ntcdntempv3.com/data/images/9169/500721/002.jpg?data=net",
      "type" : "image/jpeg",
      "bitrate" : 0,
      "duration" : 0,
      "title" : null,
      "properties" : null,
      "alternate" : null
    } ]
  }, {
    "href" : "https://raw.githubusercontent.com/tsvhcomic18alt1/comic_storage_two8/main/IMAGE/IMAGE_1a70f98b26bce0122a92571c3bcce3f5_d602b889440aaef330b2719e0ef5551d_a5d412818f9c28221565ab577be54d1e.jpg",
    "type" : "image/jpeg",
    "bitrate" : 0,
    "duration" : 0,
    "title" : null,
    "properties" : null,
    "alternate" : [ {
      "href" : "https://i221.ntcdntempv3.com/data/images/9169/500721/003.jpg?data=net",
      "type" : "image/jpeg",
      "bitrate" : 0,
      "duration" : 0,
      "title" : null,
      "properties" : null,
      "alternate" : null
    } ]
  }, {
    "href" : "https://raw.githubusercontent.com/tsvhcomic18alt1/comic_storage_two8/main/IMAGE/IMAGE_1a70f98b26bce0122a92571c3bcce3f5_d602b889440aaef330b2719e0ef5551d_838666bcd1ee4b77aef1fceb44db0442.jpg",
    "type" : "image/jpeg",
    "bitrate" : 0,
    "duration" : 0,
    "title" : null,
    "properties" : null,
    "alternate" : [ {
      "href" : "https://i221.ntcdntempv3.com/data/images/9169/500721/004.jpg?data=net",
      "type" : "image/jpeg",
      "bitrate" : 0,
      "duration" : 0,
      "title" : null,
      "properties" : null,
      "alternate" : null
    } ]
  }, {
    "href" : "https://raw.githubusercontent.com/tsvhcomic18alt1/comic_storage_two8/main/IMAGE/IMAGE_1a70f98b26bce0122a92571c3bcce3f5_d602b889440aaef330b2719e0ef5551d_52e8e2772afc8d0d8a1cc7070fd0882a.jpg",
    "type" : "image/jpeg",
    "bitrate" : 0,
    "duration" : 0,
    "title" : null,
    "properties" : null,
    "alternate" : [ {
      "href" : "https://i221.ntcdntempv3.com/data/images/9169/500721/005.jpg?data=net",
      "type" : "image/jpeg",
      "bitrate" : 0,
      "duration" : 0,
      "title" : null,
      "properties" : null,
      "alternate" : null
    } ]
  }, {
    "href" : "https://raw.githubusercontent.com/tsvhcomic18alt1/comic_storage_two8/main/IMAGE/IMAGE_1a70f98b26bce0122a92571c3bcce3f5_d602b889440aaef330b2719e0ef5551d_d3494d0754b6902ead8ad2fb48c2a64c.jpg",
    "type" : "image/jpeg",
    "bitrate" : 0,
    "duration" : 0,
    "title" : null,
    "properties" : null,
    "alternate" : [ {
      "href" : "https://i221.ntcdntempv3.com/data/images/9169/500721/006.jpg?data=net",
      "type" : "image/jpeg",
      "bitrate" : 0,
      "duration" : 0,
      "title" : null,
      "properties" : null,
      "alternate" : null
    } ]
  }, {
    "href" : "https://raw.githubusercontent.com/tsvhcomic18alt1/comic_storage_two8/main/IMAGE/IMAGE_1a70f98b26bce0122a92571c3bcce3f5_d602b889440aaef330b2719e0ef5551d_8defb1e9b336cad6202214b45670def9.jpg",
    "type" : "image/jpeg",
    "bitrate" : 0,
    "duration" : 0,
    "title" : null,
    "properties" : null,
    "alternate" : [ {
      "href" : "https://i221.ntcdntempv3.com/data/images/9169/500721/007.jpg?data=net",
      "type" : "image/jpeg",
      "bitrate" : 0,
      "duration" : 0,
      "title" : null,
      "properties" : null,
      "alternate" : null
    } ]
  }, {
    "href" : "https://raw.githubusercontent.com/tsvhcomic18alt1/comic_storage_two8/main/IMAGE/IMAGE_1a70f98b26bce0122a92571c3bcce3f5_d602b889440aaef330b2719e0ef5551d_e202d8d85e6cfacacc2e20aaaf7400c2.jpg",
    "type" : "image/jpeg",
    "bitrate" : 0,
    "duration" : 0,
    "title" : null,
    "properties" : null,
    "alternate" : [ {
      "href" : "https://i221.ntcdntempv3.com/data/images/9169/500721/008.jpg?data=net",
      "type" : "image/jpeg",
      "bitrate" : 0,
      "duration" : 0,
      "title" : null,
      "properties" : null,
      "alternate" : null
    } ]
  }, {
    "href" : "https://raw.githubusercontent.com/tsvhcomic18alt1/comic_storage_two8/main/IMAGE/IMAGE_1a70f98b26bce0122a92571c3bcce3f5_d602b889440aaef330b2719e0ef5551d_cf9d7bb4888b76d5b76dbe485eb2e216.jpg",
    "type" : "image/jpeg",
    "bitrate" : 0,
    "duration" : 0,
    "title" : null,
    "properties" : null,
    "alternate" : [ {
      "href" : "https://i221.ntcdntempv3.com/data/images/9169/500721/009.jpg?data=net",
      "type" : "image/jpeg",
      "bitrate" : 0,
      "duration" : 0,
      "title" : null,
      "properties" : null,
      "alternate" : null
    } ]
  }, {
    "href" : "https://raw.githubusercontent.com/tsvhcomic18alt1/comic_storage_two8/main/IMAGE/IMAGE_1a70f98b26bce0122a92571c3bcce3f5_d602b889440aaef330b2719e0ef5551d_c8c86544903cee9625bf8a738a5848f3.jpg",
    "type" : "image/jpeg",
    "bitrate" : 0,
    "duration" : 0,
    "title" : null,
    "properties" : null,
    "alternate" : [ {
      "href" : "https://i221.ntcdntempv3.com/data/images/9169/500721/010.jpg?data=net",
      "type" : "image/jpeg",
      "bitrate" : 0,
      "duration" : 0,
      "title" : null,
      "properties" : null,
      "alternate" : null
    } ]
  }, {
    "href" : "https://raw.githubusercontent.com/tsvhcomic18alt1/comic_storage_two8/main/IMAGE/IMAGE_1a70f98b26bce0122a92571c3bcce3f5_d602b889440aaef330b2719e0ef5551d_54cec1a9ffde156e19c35d36cb1a8d15.jpg",
    "type" : "image/jpeg",
    "bitrate" : 0,
    "duration" : 0,
    "title" : null,
    "properties" : null,
    "alternate" : [ {
      "href" : "https://i221.ntcdntempv3.com/data/images/9169/500721/011.jpg?data=net",
      "type" : "image/jpeg",
      "bitrate" : 0,
      "duration" : 0,
      "title" : null,
      "properties" : null,
      "alternate" : null
    } ]
  }, {
    "href" : "https://raw.githubusercontent.com/tsvhcomic18alt1/comic_storage_two8/main/IMAGE/IMAGE_1a70f98b26bce0122a92571c3bcce3f5_d602b889440aaef330b2719e0ef5551d_6a1303cc212675b8588a72edaca2f398.jpg",
    "type" : "image/jpeg",
    "bitrate" : 0,
    "duration" : 0,
    "title" : null,
    "properties" : null,
    "alternate" : [ {
      "href" : "https://i221.ntcdntempv3.com/data/images/9169/500721/012.jpg?data=net",
      "type" : "image/jpeg",
      "bitrate" : 0,
      "duration" : 0,
      "title" : null,
      "properties" : null,
      "alternate" : null
    } ]
  }, {
    "href" : "https://raw.githubusercontent.com/tsvhcomic18alt1/comic_storage_two8/main/IMAGE/IMAGE_1a70f98b26bce0122a92571c3bcce3f5_d602b889440aaef330b2719e0ef5551d_260481b322bfd2c02e96cf4f1f0342aa.jpg",
    "type" : "image/jpeg",
    "bitrate" : 0,
    "duration" : 0,
    "title" : null,
    "properties" : null,
    "alternate" : [ {
      "href" : "https://i221.ntcdntempv3.com/data/images/9169/500721/013.jpg?data=net",
      "type" : "image/jpeg",
      "bitrate" : 0,
      "duration" : 0,
      "title" : null,
      "properties" : null,
      "alternate" : null
    } ]
  } ],
  "toc" : null,
  "@context" : "https://readium.org/webpub-manifest/context.jsonld"
}